README.md
setup.py
BaseMountRetrieve/__init__.py
BaseMountRetrieve/basemountretrieve.py
BaseMountRetrieve.egg-info/PKG-INFO
BaseMountRetrieve.egg-info/SOURCES.txt
BaseMountRetrieve.egg-info/dependency_links.txt
BaseMountRetrieve.egg-info/entry_points.txt
BaseMountRetrieve.egg-info/requires.txt
BaseMountRetrieve.egg-info/top_level.txt