Metadata-Version: 2.1
Name: BaseMountRetrieve
Version: 0.7.1
Summary: Internal BFSSI package for retrieving files from BaseMount
Home-page: https://github.com/bfssi-forest-dussault/BaseMountRetrieve
Author: Forest Dussault
Author-email: forest.dussault@canada.ca
License: UNKNOWN
Platform: UNKNOWN
